pending.py
pending-1.3.dist-info/LICENSE
pending-1.3.dist-info/METADATA
pending-1.3.dist-info/WHEEL
pending-1.3.dist-info/top_level.txt
pending-1.3.dist-info/zip-safe
pending-1.3.dist-info/RECORD
