Metadata-Version: 2.1
Name: pending
Version: 1.3
Summary: pending time-delayed events scheduling
Home-page: https://github.com/koodaamo/pending
Author: Petri Savolainen
Author-email: petri@koodaamo.fi
License: GPLv2
Keywords: events,timer,asyncio
Platform: UNKNOWN
Classifier: License :: OSI Approved :: GNU General Public License v2 (GPLv2)
Classifier: Programming Language :: Python :: 3
Classifier: Programming Language :: Python :: 3.10
License-File: LICENSE
